{
  "imports": {
    "class": "imports",
    "CISCO-SMI": [
      "ciscoAgentCapability"
    ],
    "SNMPv2-CONF": [
      "MODULE-COMPLIANCE",
      "NOTIFICATION-GROUP",
      "AGENT-CAPABILITIES"
    ],
    "SNMPv2-SMI": [
      "Bits",
      "iso",
      "MODULE-IDENTITY",
      "Unsigned32",
      "Gauge32",
      "NOTIFICATION-TYPE",
      "MibIdentifier",
      "TimeTicks",
      "Counter32",
      "OBJECT-TYPE",
      "OBJECT-IDENTITY",
      "IpAddress",
      "Counter64",
      "Integer32"
    ],
    "SNMPv2-TC": [
      "DisplayString",
      "TEXTUAL-CONVENTION",
      "TruthValue"
    ]
  },
  "ciscoAaaClientCapability": {
    "name": "ciscoAaaClientCapability",
    "oid": "1.3.6.1.4.1.9.7.322",
    "class": "moduleidentity",
    "revisions": [
      {
        "revision": "2004-02-03 00:00",
        "description": "Added VARIATION for cacEnable and cacPrimaryMethod."
      },
      {
        "revision": "2003-08-06 00:00",
        "description": "Initial version of this MIB module."
      }
    ]
  },
  "ciscoAaaClientCapCatOSV08R0101": {
    "name": "ciscoAaaClientCapCatOSV08R0101",
    "oid": "1.3.6.1.4.1.9.7.322.1",
    "class": "agentcapabilities",
    "productrelease": "Cisco CatOS 8.1(1) on Catalyst 6000/6500\n                         and Cisco 7600 series devices.",
    "status": "current"
  },
  "meta": {
    "comments": [
      "ASN.1 source file:///home/runner/work/mibs/mibs/src/vendor/cisco/CISCO-AAA-CLIENT-CAPABILITY",
      "Produced by pysmi-1.1.8 at Fri Jan 27 13:56:32 2023",
      "On host fv-az401-610 platform Linux version 5.15.0-1031-azure by user runner",
      "Using Python version 3.10.9 (main, Dec  7 2022, 08:16:13) [GCC 11.3.0]"
    ],
    "module": "CISCO-AAA-CLIENT-CAPABILITY"
  }
}