{
  "imports": {
    "class": "imports",
    "CISCO-SMI": [
      "ciscoAgentCapability"
    ],
    "SNMPv2-CONF": [
      "NOTIFICATION-GROUP",
      "AGENT-CAPABILITIES",
      "MODULE-COMPLIANCE"
    ],
    "SNMPv2-SMI": [
      "Unsigned32",
      "NOTIFICATION-TYPE",
      "Bits",
      "MibIdentifier",
      "Gauge32",
      "MODULE-IDENTITY",
      "Counter32",
      "TimeTicks",
      "Integer32",
      "IpAddress",
      "OBJECT-IDENTITY",
      "Counter64",
      "OBJECT-TYPE",
      "iso"
    ],
    "SNMPv2-TC": [
      "TEXTUAL-CONVENTION",
      "DisplayString"
    ]
  },
  "ciscoThreatMitigationServiceCapability": {
    "name": "ciscoThreatMitigationServiceCapability",
    "oid": "1.3.6.1.4.1.9.7.532",
    "class": "moduleidentity",
    "revisions": [
      {
        "revision": "2007-05-17 00:00",
        "description": "Added the agent capabilities statement for ciscoTmsCapIOSV12R05T."
      },
      {
        "revision": "2007-01-29 00:00",
        "description": "Initial version of this MIB module."
      }
    ]
  },
  "ciscoTmsCapIOSV12R02S": {
    "name": "ciscoTmsCapIOSV12R02S",
    "oid": "1.3.6.1.4.1.9.7.532.1",
    "class": "agentcapabilities",
    "productrelease": "Cisco IOS 12.2S ",
    "status": "current"
  },
  "ciscoTmsCapIOSV12R05T": {
    "name": "ciscoTmsCapIOSV12R05T",
    "oid": "1.3.6.1.4.1.9.7.532.2",
    "class": "agentcapabilities",
    "productrelease": "Cisco IOS 12.5T",
    "status": "current"
  },
  "meta": {
    "comments": [
      "ASN.1 source file:///home/runner/work/mibs/mibs/src/vendor/cisco/CISCO-THREAT-MITIGATION-SERVICE-CAPABILITY",
      "Produced by pysmi-1.1.8 at Mon Jan 17 19:22:46 2022",
      "On host fv-az36-128 platform Linux version 5.11.0-1025-azure by user runner",
      "Using Python version 3.10.1 (main, Dec 22 2021, 10:45:09) [GCC 9.3.0]"
    ],
    "module": "CISCO-THREAT-MITIGATION-SERVICE-CAPABILITY"
  }
}