{
  "imports": {
    "class": "imports",
    "CISCO-SMI": [
      "ciscoAgentCapability"
    ],
    "SNMPv2-CONF": [
      "MODULE-COMPLIANCE",
      "NOTIFICATION-GROUP",
      "AGENT-CAPABILITIES"
    ],
    "SNMPv2-SMI": [
      "OBJECT-IDENTITY",
      "MODULE-IDENTITY",
      "NOTIFICATION-TYPE",
      "MibIdentifier",
      "iso",
      "Counter32",
      "OBJECT-TYPE",
      "Unsigned32",
      "Integer32",
      "Bits",
      "IpAddress",
      "TimeTicks",
      "Counter64",
      "Gauge32"
    ],
    "SNMPv2-TC": [
      "TEXTUAL-CONVENTION",
      "DisplayString"
    ]
  },
  "ciscoMldSnoopingCapability": {
    "name": "ciscoMldSnoopingCapability",
    "oid": "1.3.6.1.4.1.9.7.586",
    "class": "moduleidentity",
    "revisions": [
      {
        "revision": "2010-03-02 00:00",
        "description": "Initial version of this MIB module."
      }
    ]
  },
  "ciscoMldSnoopingCapabilityV04R01": {
    "name": "ciscoMldSnoopingCapabilityV04R01",
    "oid": "1.3.6.1.4.1.9.7.586.1",
    "class": "agentcapabilities",
    "productrelease": "Cisco IOS-XR",
    "status": "current"
  },
  "meta": {
    "comments": [
      "ASN.1 source file:///home/runner/work/mibs/mibs/src/vendor/cisco/CISCO-MLD-SNOOPING-CAPABILITY",
      "Produced by pysmi-1.1.10 at Mon Oct 30 02:16:46 2023",
      "On host fv-az443-612 platform Linux version 6.2.0-1015-azure by user runner",
      "Using Python version 3.10.13 (main, Aug 28 2023, 08:28:42) [GCC 11.4.0]"
    ],
    "module": "CISCO-MLD-SNOOPING-CAPABILITY"
  }
}