{
  "imports": {
    "class": "imports",
    "CISCO-SMI": [
      "ciscoAgentCapability"
    ],
    "SNMPv2-CONF": [
      "AGENT-CAPABILITIES",
      "MODULE-COMPLIANCE",
      "NOTIFICATION-GROUP"
    ],
    "SNMPv2-SMI": [
      "IpAddress",
      "MODULE-IDENTITY",
      "MibIdentifier",
      "Integer32",
      "TimeTicks",
      "Gauge32",
      "Bits",
      "Counter64",
      "Counter32",
      "iso",
      "OBJECT-IDENTITY",
      "OBJECT-TYPE",
      "NOTIFICATION-TYPE",
      "Unsigned32"
    ],
    "SNMPv2-TC": [
      "TEXTUAL-CONVENTION",
      "DisplayString"
    ]
  },
  "cftpclientCapability": {
    "name": "cftpclientCapability",
    "oid": "1.3.6.1.4.1.9.7.483",
    "class": "moduleidentity",
    "revisions": [
      {
        "revision": "2006-01-02 00:00",
        "description": "Initial version of this MIB module."
      }
    ]
  },
  "cftpclientCapabilityIOSXRV2R0CRS1": {
    "name": "cftpclientCapabilityIOSXRV2R0CRS1",
    "oid": "1.3.6.1.4.1.9.7.483.1",
    "class": "agentcapabilities",
    "productrelease": "Cisco IOS XR 2.0 for CRS-1",
    "status": "current"
  },
  "meta": {
    "comments": [
      "ASN.1 source file:///home/runner/work/mibs/mibs/src/vendor/cisco/CISCO-FTP-CLIENT-CAPABILITY",
      "Produced by pysmi-1.1.12 at Mon Oct  7 02:55:11 2024",
      "On host fv-az775-99 platform Linux version 6.8.0-1014-azure by user runner",
      "Using Python version 3.10.15 (main, Sep  9 2024, 03:02:45) [GCC 11.4.0]"
    ],
    "module": "CISCO-FTP-CLIENT-CAPABILITY"
  }
}