{
  "imports": {
    "class": "imports",
    "CTRON-SSR-SMI-MIB": [
      "ssrMibs"
    ],
    "SNMPv2-CONF": [
      "NOTIFICATION-GROUP",
      "MODULE-COMPLIANCE",
      "OBJECT-GROUP"
    ],
    "SNMPv2-SMI": [
      "MODULE-IDENTITY",
      "IpAddress",
      "Counter64",
      "MibIdentifier",
      "Counter32",
      "OBJECT-IDENTITY",
      "Bits",
      "Gauge32",
      "NOTIFICATION-TYPE",
      "Integer32",
      "OBJECT-TYPE",
      "Unsigned32",
      "iso",
      "TimeTicks"
    ],
    "SNMPv2-TC": [
      "TEXTUAL-CONVENTION",
      "DisplayString"
    ]
  },
  "hardwareMIB": {
    "name": "hardwareMIB",
    "oid": "1.3.6.1.4.1.52.2501.1.200",
    "class": "moduleidentity",
    "revisions": [
      {
        "revision": "2000-07-17 00:00",
        "description": "Add support for the Smart Switch 6000 2 Port Gigabit Backplane module to the SSRModuleType for the Enterasys SSR product line"
      },
      {
        "revision": "2000-07-15 00:00",
        "description": "Update contact information. This mib is found on Riverstone Networks RS product line as well as Enterasys SSR product line"
      },
      {
        "revision": "2000-05-31 00:00",
        "description": "Modify SSRPortConnectorType for GBIC connector in 4.0 and update sysHwModuleService by appending the board serial number for 4.0 for RS-32000."
      },
      {
        "revision": "2000-03-20 00:00",
        "description": "Add Firmware 4.0 support. 3200 series modules, gigabit modules with GBIC support."
      },
      {
        "revision": "1999-12-30 00:00",
        "description": "Add Firmware 3.1 support. 16 port 10/100 TX, Gigabit over Copper, ATM OC-3, POS OC3/12."
      },
      {
        "revision": "1999-01-20 00:00",
        "description": "Add Firmware 3.0 support. Add Backup control module status and last Hotswap event."
      },
      {
        "revision": "1998-08-04 00:00",
        "description": "First Revision of SSR Hardware mib. "
      }
    ]
  },
  "SSRInterfaceIndex": {
    "name": "SSRInterfaceIndex",
    "class": "textualconvention",
    "type": {
      "type": "INTEGER",
      "class": "type",
      "constraints": {
        "range": [
          {
            "min": 0,
            "max": 65535
          }
        ]
      }
    },
    "status": "current"
  },
  "SSRModuleType": {
    "name": "SSRModuleType",
    "class": "textualconvention",
    "type": {
      "type": "INTEGER",
      "class": "type",
      "constraints": {
        "enumeration": {
          "controlModule": 1,
          "ether100TX": 2,
          "ether100FX": 3,
          "gigabitSX": 4,
          "gigabitLX": 5,
          "serial4port": 6,
          "hssi": 7,
          "unknown": 8,
          "gigabitLLX": 9,
          "none": 10,
          "controlModule2": 11,
          "gigabitLLX2P": 12,
          "serial2port": 13,
          "cmts1x4port": 15,
          "fddi2port": 16,
          "controlModule3": 17,
          "serial4portCE": 20,
          "ether100TX16port": 21,
          "gigabitTX": 22,
          "atm155": 24,
          "sonet4PortOc3": 25,
          "sonet2PortOc12": 26,
          "gigabitFX4P": 27,
          "gigabitFX4PGBIC": 28,
          "gigabitFX2PGBIC": 29,
          "gigabit6K2PBP": 30,
          "rbGigabit8PGBIC": 503,
          "rbGigabit4PGBIC": 504,
          "rbEther100TX24P": 505,
          "rbEther100TC32P": 506,
          "rbControlModule": 507
        }
      }
    },
    "status": "current"
  },
  "SSRModuleStatus": {
    "name": "SSRModuleStatus",
    "class": "textualconvention",
    "type": {
      "type": "INTEGER",
      "class": "type",
      "constraints": {
        "enumeration": {
          "online": 1,
          "offline": 2
        }
      }
    },
    "status": "current"
  },
  "SSRPortType": {
    "name": "SSRPortType",
    "class": "textualconvention",
    "type": {
      "type": "INTEGER",
      "class": "type",
      "constraints": {
        "enumeration": {
          "etherFast": 1,
          "gigEther": 2,
          "hssi": 3,
          "serial": 4,
          "unknown": 5,
          "sonet": 6,
          "ds1": 7,
          "ds3": 8,
          "cmt": 9,
          "e1": 10,
          "e3": 11,
          "fddi": 12
        }
      }
    },
    "status": "current"
  },
  "SSRPortConnectorType": {
    "name": "SSRPortConnectorType",
    "class": "textualconvention",
    "type": {
      "type": "INTEGER",
      "class": "type",
      "constraints": {
        "enumeration": {
          "empty": 0,
          "db9m": 1,
          "db9f": 2,
          "db15m": 3,
          "db15f": 4,
          "db25m": 5,
          "db25f": 6,
          "rj11": 7,
          "rj45": 8,
          "aui": 9,
          "ftypef": 10,
          "fiberScMM": 11,
          "v35": 12,
          "eia530": 13,
          "rs44x": 14,
          "x21": 15,
          "hssi": 16,
          "unknown": 17,
          "fiberScSM": 18,
          "fiberMTRjMM": 19,
          "fiberMTRjSM": 20,
          "bncf": 21,
          "bncm": 22,
          "rj21": 23,
          "fiberScSMLH": 24
        }
      }
    },
    "status": "current"
  },
  "SSRserviceType": {
    "name": "SSRserviceType",
    "class": "textualconvention",
    "type": {
      "type": "OCTET STRING",
      "class": "type",
      "constraints": {
        "size": [
          {
            "min": 0,
            "max": 7
          }
        ]
      }
    },
    "status": "current"
  },
  "SSRmemorySize": {
    "name": "SSRmemorySize",
    "class": "textualconvention",
    "type": {
      "type": "INTEGER",
      "class": "type",
      "constraints": {
        "range": [
          {
            "min": -1,
            "max": 2147483647
          }
        ]
      }
    },
    "status": "current"
  },
  "SSRSwitchingFabricInfo": {
    "name": "SSRSwitchingFabricInfo",
    "class": "textualconvention",
    "type": {
      "type": "INTEGER",
      "class": "type",
      "constraints": {
        "range": [
          {
            "min": 0,
            "max": 63
          }
        ]
      }
    },
    "status": "current"
  },
  "SSRCmLedState": {
    "name": "SSRCmLedState",
    "class": "textualconvention",
    "type": {
      "type": "INTEGER",
      "class": "type",
      "constraints": {
        "range": [
          {
            "min": 0,
            "max": 15
          }
        ]
      }
    },
    "status": "current"
  },
  "SSRBackupCMState": {
    "name": "SSRBackupCMState",
    "class": "textualconvention",
    "type": {
      "type": "INTEGER",
      "class": "type",
      "constraints": {
        "enumeration": {
          "unknown": 1,
          "inactive": 2,
          "standby": 3,
          "notInstalled": 4,
          "active": 5
        }
      }
    },
    "status": "current"
  },
  "sysHwGroup": {
    "name": "sysHwGroup",
    "oid": "1.3.6.1.4.1.52.2501.1.1",
    "class": "objectidentity"
  },
  "sysHwNumSlots": {
    "name": "sysHwNumSlots",
    "oid": "1.3.6.1.4.1.52.2501.1.1.1",
    "nodetype": "scalar",
    "class": "objecttype",
    "syntax": {
      "type": "INTEGER",
      "class": "type",
      "constraints": {
        "range": [
          {
            "min": 0,
            "max": 64
          }
        ]
      }
    },
    "maxaccess": "read-only",
    "status": "current"
  },
  "sysHwModuleTable": {
    "name": "sysHwModuleTable",
    "oid": "1.3.6.1.4.1.52.2501.1.1.2",
    "nodetype": "table",
    "class": "objecttype",
    "maxaccess": "not-accessible",
    "status": "current"
  },
  "sysHwModuleEntry": {
    "name": "sysHwModuleEntry",
    "oid": "1.3.6.1.4.1.52.2501.1.1.2.1",
    "nodetype": "row",
    "class": "objecttype",
    "maxaccess": "not-accessible",
    "indices": [
      {
        "module": "CTRON-SSR-HARDWARE-MIB",
        "object": "sysHwModuleSlotNumber",
        "implied": 0
      }
    ],
    "status": "current"
  },
  "sysHwModuleSlotNumber": {
    "name": "sysHwModuleSlotNumber",
    "oid": "1.3.6.1.4.1.52.2501.1.1.2.1.1",
    "nodetype": "column",
    "class": "objecttype",
    "syntax": {
      "type": "INTEGER",
      "class": "type",
      "constraints": {
        "range": [
          {
            "min": 1,
            "max": 65
          }
        ]
      }
    },
    "maxaccess": "read-only",
    "status": "current"
  },
  "sysHwModuleType": {
    "name": "sysHwModuleType",
    "oid": "1.3.6.1.4.1.52.2501.1.1.2.1.2",
    "nodetype": "column",
    "class": "objecttype",
    "syntax": {
      "type": "SSRModuleType",
      "class": "type"
    },
    "maxaccess": "read-only",
    "status": "current"
  },
  "sysHwModuleDesc": {
    "name": "sysHwModuleDesc",
    "oid": "1.3.6.1.4.1.52.2501.1.1.2.1.3",
    "nodetype": "column",
    "class": "objecttype",
    "syntax": {
      "type": "OCTET STRING",
      "class": "type",
      "constraints": {
        "size": [
          {
            "min": 0,
            "max": 255
          }
        ]
      }
    },
    "maxaccess": "read-only",
    "status": "current"
  },
  "sysHwModuleNumPorts": {
    "name": "sysHwModuleNumPorts",
    "oid": "1.3.6.1.4.1.52.2501.1.1.2.1.4",
    "nodetype": "column",
    "class": "objecttype",
    "syntax": {
      "type": "INTEGER",
      "class": "type",
      "constraints": {
        "range": [
          {
            "min": 0,
            "max": 256
          }
        ]
      }
    },
    "maxaccess": "read-only",
    "status": "current"
  },
  "sysHwModuleVersion": {
    "name": "sysHwModuleVersion",
    "oid": "1.3.6.1.4.1.52.2501.1.1.2.1.5",
    "nodetype": "column",
    "class": "objecttype",
    "syntax": {
      "type": "OCTET STRING",
      "class": "type",
      "constraints": {
        "size": [
          {
            "min": 1,
            "max": 1
          }
        ]
      }
    },
    "maxaccess": "read-only",
    "status": "current"
  },
  "sysHwModuleMemory": {
    "name": "sysHwModuleMemory",
    "oid": "1.3.6.1.4.1.52.2501.1.1.2.1.6",
    "nodetype": "column",
    "class": "objecttype",
    "syntax": {
      "type": "SSRmemorySize",
      "class": "type"
    },
    "maxaccess": "read-only",
    "status": "current"
  },
  "sysHwModuleService": {
    "name": "sysHwModuleService",
    "oid": "1.3.6.1.4.1.52.2501.1.1.2.1.8",
    "nodetype": "column",
    "class": "objecttype",
    "syntax": {
      "type": "SSRserviceType",
      "class": "type"
    },
    "maxaccess": "read-only",
    "status": "current"
  },
  "sysHwModuleStatus": {
    "name": "sysHwModuleStatus",
    "oid": "1.3.6.1.4.1.52.2501.1.1.2.1.9",
    "nodetype": "column",
    "class": "objecttype",
    "syntax": {
      "type": "SSRModuleStatus",
      "class": "type"
    },
    "maxaccess": "read-only",
    "status": "current"
  },
  "sysHwPortTable": {
    "name": "sysHwPortTable",
    "oid": "1.3.6.1.4.1.52.2501.1.1.3",
    "nodetype": "table",
    "class": "objecttype",
    "maxaccess": "not-accessible",
    "status": "current"
  },
  "sysHwPortEntry": {
    "name": "sysHwPortEntry",
    "oid": "1.3.6.1.4.1.52.2501.1.1.3.1",
    "nodetype": "row",
    "class": "objecttype",
    "maxaccess": "not-accessible",
    "indices": [
      {
        "module": "CTRON-SSR-HARDWARE-MIB",
        "object": "sysHwPortSlotNumber",
        "implied": 0
      },
      {
        "module": "CTRON-SSR-HARDWARE-MIB",
        "object": "sysHwPortNumber",
        "implied": 0
      }
    ],
    "status": "current"
  },
  "sysHwPortSlotNumber": {
    "name": "sysHwPortSlotNumber",
    "oid": "1.3.6.1.4.1.52.2501.1.1.3.1.1",
    "nodetype": "column",
    "class": "objecttype",
    "syntax": {
      "type": "INTEGER",
      "class": "type",
      "constraints": {
        "range": [
          {
            "min": 1,
            "max": 255
          }
        ]
      }
    },
    "maxaccess": "read-only",
    "status": "current"
  },
  "sysHwPortNumber": {
    "name": "sysHwPortNumber",
    "oid": "1.3.6.1.4.1.52.2501.1.1.3.1.2",
    "nodetype": "column",
    "class": "objecttype",
    "syntax": {
      "type": "INTEGER",
      "class": "type",
      "constraints": {
        "range": [
          {
            "min": 1,
            "max": 255
          }
        ]
      }
    },
    "maxaccess": "read-only",
    "status": "current"
  },
  "sysHwPortType": {
    "name": "sysHwPortType",
    "oid": "1.3.6.1.4.1.52.2501.1.1.3.1.3",
    "nodetype": "column",
    "class": "objecttype",
    "syntax": {
      "type": "SSRPortType",
      "class": "type"
    },
    "maxaccess": "read-only",
    "status": "current"
  },
  "sysHwPortConnectorType": {
    "name": "sysHwPortConnectorType",
    "oid": "1.3.6.1.4.1.52.2501.1.1.3.1.4",
    "nodetype": "column",
    "class": "objecttype",
    "syntax": {
      "type": "SSRPortConnectorType",
      "class": "type"
    },
    "maxaccess": "read-only",
    "status": "current"
  },
  "sysHwPortIfIndex": {
    "name": "sysHwPortIfIndex",
    "oid": "1.3.6.1.4.1.52.2501.1.1.3.1.5",
    "nodetype": "column",
    "class": "objecttype",
    "syntax": {
      "type": "SSRInterfaceIndex",
      "class": "type"
    },
    "maxaccess": "read-only",
    "status": "current"
  },
  "PowerSupplyBits": {
    "name": "PowerSupplyBits",
    "class": "textualconvention",
    "type": {
      "type": "INTEGER",
      "class": "type",
      "constraints": {
        "range": [
          {
            "min": 0,
            "max": 255
          }
        ]
      }
    },
    "status": "current"
  },
  "sysHwPowerSupply": {
    "name": "sysHwPowerSupply",
    "oid": "1.3.6.1.4.1.52.2501.1.1.4",
    "nodetype": "scalar",
    "class": "objecttype",
    "syntax": {
      "type": "PowerSupplyBits",
      "class": "type"
    },
    "maxaccess": "read-only",
    "status": "current"
  },
  "sysHwFan": {
    "name": "sysHwFan",
    "oid": "1.3.6.1.4.1.52.2501.1.1.5",
    "nodetype": "scalar",
    "class": "objecttype",
    "syntax": {
      "type": "INTEGER",
      "class": "type",
      "constraints": {
        "enumeration": {
          "working": 1,
          "notWorking": 2,
          "unknown": 3
        }
      }
    },
    "maxaccess": "read-only",
    "status": "current"
  },
  "sysHwTemperature": {
    "name": "sysHwTemperature",
    "oid": "1.3.6.1.4.1.52.2501.1.1.6",
    "nodetype": "scalar",
    "class": "objecttype",
    "syntax": {
      "type": "INTEGER",
      "class": "type",
      "constraints": {
        "enumeration": {
          "normal": 1,
          "outOfRange": 2,
          "unknown": 3
        }
      }
    },
    "maxaccess": "read-only",
    "status": "current"
  },
  "sysHwChassisId": {
    "name": "sysHwChassisId",
    "oid": "1.3.6.1.4.1.52.2501.1.1.7",
    "nodetype": "scalar",
    "class": "objecttype",
    "syntax": {
      "type": "OCTET STRING",
      "class": "type",
      "constraints": {
        "size": [
          {
            "min": 0,
            "max": 255
          }
        ]
      }
    },
    "maxaccess": "read-only",
    "status": "current"
  },
  "sysHwSwitchingFabric": {
    "name": "sysHwSwitchingFabric",
    "oid": "1.3.6.1.4.1.52.2501.1.1.19",
    "nodetype": "scalar",
    "class": "objecttype",
    "syntax": {
      "type": "SSRSwitchingFabricInfo",
      "class": "type"
    },
    "maxaccess": "read-only",
    "status": "current"
  },
  "sysHwControlModuleLED": {
    "name": "sysHwControlModuleLED",
    "oid": "1.3.6.1.4.1.52.2501.1.1.20",
    "nodetype": "scalar",
    "class": "objecttype",
    "syntax": {
      "type": "SSRCmLedState",
      "class": "type"
    },
    "maxaccess": "read-only",
    "status": "current"
  },
  "sysHwControlModuleBackupState": {
    "name": "sysHwControlModuleBackupState",
    "oid": "1.3.6.1.4.1.52.2501.1.1.21",
    "nodetype": "scalar",
    "class": "objecttype",
    "syntax": {
      "type": "SSRBackupCMState",
      "class": "type"
    },
    "maxaccess": "read-only",
    "status": "current"
  },
  "sysHwLastHotSwapEvent": {
    "name": "sysHwLastHotSwapEvent",
    "oid": "1.3.6.1.4.1.52.2501.1.1.22",
    "nodetype": "scalar",
    "class": "objecttype",
    "syntax": {
      "type": "TimeTicks",
      "class": "type"
    },
    "maxaccess": "read-only",
    "status": "current"
  },
  "sysHwTotalInOctets": {
    "name": "sysHwTotalInOctets",
    "oid": "1.3.6.1.4.1.52.2501.1.1.10",
    "nodetype": "scalar",
    "class": "objecttype",
    "syntax": {
      "type": "Counter64",
      "class": "type"
    },
    "maxaccess": "read-only",
    "status": "deprecated"
  },
  "sysHwTotalOutOctets": {
    "name": "sysHwTotalOutOctets",
    "oid": "1.3.6.1.4.1.52.2501.1.1.11",
    "nodetype": "scalar",
    "class": "objecttype",
    "syntax": {
      "type": "Counter64",
      "class": "type"
    },
    "maxaccess": "read-only",
    "status": "deprecated"
  },
  "sysHwTotalInFrames": {
    "name": "sysHwTotalInFrames",
    "oid": "1.3.6.1.4.1.52.2501.1.1.12",
    "nodetype": "scalar",
    "class": "objecttype",
    "syntax": {
      "type": "Counter64",
      "class": "type"
    },
    "maxaccess": "read-only",
    "status": "deprecated"
  },
  "sysHwTotalOutFrames": {
    "name": "sysHwTotalOutFrames",
    "oid": "1.3.6.1.4.1.52.2501.1.1.13",
    "nodetype": "scalar",
    "class": "objecttype",
    "syntax": {
      "type": "Counter64",
      "class": "type"
    },
    "maxaccess": "read-only",
    "status": "deprecated"
  },
  "sysHwTotalL2SwitchedFrames": {
    "name": "sysHwTotalL2SwitchedFrames",
    "oid": "1.3.6.1.4.1.52.2501.1.1.14",
    "nodetype": "scalar",
    "class": "objecttype",
    "syntax": {
      "type": "Counter64",
      "class": "type"
    },
    "maxaccess": "read-only",
    "status": "deprecated"
  },
  "sysHwTotalL3SwitchedFrames": {
    "name": "sysHwTotalL3SwitchedFrames",
    "oid": "1.3.6.1.4.1.52.2501.1.1.15",
    "nodetype": "scalar",
    "class": "objecttype",
    "syntax": {
      "type": "Counter64",
      "class": "type"
    },
    "maxaccess": "read-only",
    "status": "deprecated"
  },
  "hwConformance": {
    "name": "hwConformance",
    "oid": "1.3.6.1.4.1.52.2501.1.200.2",
    "class": "objectidentity"
  },
  "hwCompliances": {
    "name": "hwCompliances",
    "oid": "1.3.6.1.4.1.52.2501.1.200.2.1",
    "class": "objectidentity"
  },
  "hwGroups": {
    "name": "hwGroups",
    "oid": "1.3.6.1.4.1.52.2501.1.200.2.2",
    "class": "objectidentity"
  },
  "hwComplianceV10": {
    "name": "hwComplianceV10",
    "oid": "1.3.6.1.4.1.52.2501.1.200.2.2.1.1",
    "class": "modulecompliance",
    "modulecompliance": [
      {
        "object": "hwConfGroupV10",
        "module": "CTRON-SSR-HARDWARE-MIB"
      }
    ],
    "status": "deprecated"
  },
  "hwComplianceV11": {
    "name": "hwComplianceV11",
    "oid": "1.3.6.1.4.1.52.2501.1.200.2.2.2.2",
    "class": "modulecompliance",
    "modulecompliance": [
      {
        "object": "hwConfGroupV11",
        "module": "CTRON-SSR-HARDWARE-MIB"
      }
    ],
    "status": "deprecated"
  },
  "hwComplianceV12": {
    "name": "hwComplianceV12",
    "oid": "1.3.6.1.4.1.52.2501.1.200.2.2.2.3",
    "class": "modulecompliance",
    "modulecompliance": [
      {
        "object": "hwConfGroupV11",
        "module": "CTRON-SSR-HARDWARE-MIB"
      }
    ],
    "status": "deprecated"
  },
  "hwComplianceV30": {
    "name": "hwComplianceV30",
    "oid": "1.3.6.1.4.1.52.2501.1.200.2.2.2.4",
    "class": "modulecompliance",
    "modulecompliance": [
      {
        "object": "hwConfGroupV30",
        "module": "CTRON-SSR-HARDWARE-MIB"
      }
    ],
    "status": "current"
  },
  "hwConfGroupV10": {
    "name": "hwConfGroupV10",
    "oid": "1.3.6.1.4.1.52.2501.1.200.2.2.1",
    "class": "objectgroup",
    "objects": [
      {
        "module": "CTRON-SSR-HARDWARE-MIB",
        "object": "sysHwNumSlots"
      },
      {
        "module": "CTRON-SSR-HARDWARE-MIB",
        "object": "sysHwModuleSlotNumber"
      },
      {
        "module": "CTRON-SSR-HARDWARE-MIB",
        "object": "sysHwModuleType"
      },
      {
        "module": "CTRON-SSR-HARDWARE-MIB",
        "object": "sysHwModuleDesc"
      },
      {
        "module": "CTRON-SSR-HARDWARE-MIB",
        "object": "sysHwModuleNumPorts"
      },
      {
        "module": "CTRON-SSR-HARDWARE-MIB",
        "object": "sysHwModuleVersion"
      },
      {
        "module": "CTRON-SSR-HARDWARE-MIB",
        "object": "sysHwPortSlotNumber"
      },
      {
        "module": "CTRON-SSR-HARDWARE-MIB",
        "object": "sysHwPortNumber"
      },
      {
        "module": "CTRON-SSR-HARDWARE-MIB",
        "object": "sysHwPortType"
      },
      {
        "module": "CTRON-SSR-HARDWARE-MIB",
        "object": "sysHwPortConnectorType"
      },
      {
        "module": "CTRON-SSR-HARDWARE-MIB",
        "object": "sysHwPortIfIndex"
      },
      {
        "module": "CTRON-SSR-HARDWARE-MIB",
        "object": "sysHwPowerSupply"
      },
      {
        "module": "CTRON-SSR-HARDWARE-MIB",
        "object": "sysHwFan"
      },
      {
        "module": "CTRON-SSR-HARDWARE-MIB",
        "object": "sysHwTemperature"
      },
      {
        "module": "CTRON-SSR-HARDWARE-MIB",
        "object": "sysHwChassisId"
      },
      {
        "module": "CTRON-SSR-HARDWARE-MIB",
        "object": "sysHwTotalInOctets"
      },
      {
        "module": "CTRON-SSR-HARDWARE-MIB",
        "object": "sysHwTotalOutOctets"
      },
      {
        "module": "CTRON-SSR-HARDWARE-MIB",
        "object": "sysHwTotalInFrames"
      },
      {
        "module": "CTRON-SSR-HARDWARE-MIB",
        "object": "sysHwTotalOutFrames"
      },
      {
        "module": "CTRON-SSR-HARDWARE-MIB",
        "object": "sysHwTotalL2SwitchedFrames"
      },
      {
        "module": "CTRON-SSR-HARDWARE-MIB",
        "object": "sysHwTotalL3SwitchedFrames"
      }
    ],
    "status": "deprecated"
  },
  "hwConfGroupV11": {
    "name": "hwConfGroupV11",
    "oid": "1.3.6.1.4.1.52.2501.1.200.2.2.2",
    "class": "objectgroup",
    "objects": [
      {
        "module": "CTRON-SSR-HARDWARE-MIB",
        "object": "sysHwNumSlots"
      },
      {
        "module": "CTRON-SSR-HARDWARE-MIB",
        "object": "sysHwModuleSlotNumber"
      },
      {
        "module": "CTRON-SSR-HARDWARE-MIB",
        "object": "sysHwModuleType"
      },
      {
        "module": "CTRON-SSR-HARDWARE-MIB",
        "object": "sysHwModuleDesc"
      },
      {
        "module": "CTRON-SSR-HARDWARE-MIB",
        "object": "sysHwModuleNumPorts"
      },
      {
        "module": "CTRON-SSR-HARDWARE-MIB",
        "object": "sysHwModuleVersion"
      },
      {
        "module": "CTRON-SSR-HARDWARE-MIB",
        "object": "sysHwModuleMemory"
      },
      {
        "module": "CTRON-SSR-HARDWARE-MIB",
        "object": "sysHwModuleService"
      },
      {
        "module": "CTRON-SSR-HARDWARE-MIB",
        "object": "sysHwPortSlotNumber"
      },
      {
        "module": "CTRON-SSR-HARDWARE-MIB",
        "object": "sysHwPortNumber"
      },
      {
        "module": "CTRON-SSR-HARDWARE-MIB",
        "object": "sysHwPortType"
      },
      {
        "module": "CTRON-SSR-HARDWARE-MIB",
        "object": "sysHwPortConnectorType"
      },
      {
        "module": "CTRON-SSR-HARDWARE-MIB",
        "object": "sysHwPortIfIndex"
      },
      {
        "module": "CTRON-SSR-HARDWARE-MIB",
        "object": "sysHwPowerSupply"
      },
      {
        "module": "CTRON-SSR-HARDWARE-MIB",
        "object": "sysHwFan"
      },
      {
        "module": "CTRON-SSR-HARDWARE-MIB",
        "object": "sysHwTemperature"
      },
      {
        "module": "CTRON-SSR-HARDWARE-MIB",
        "object": "sysHwChassisId"
      },
      {
        "module": "CTRON-SSR-HARDWARE-MIB",
        "object": "sysHwSwitchingFabric"
      },
      {
        "module": "CTRON-SSR-HARDWARE-MIB",
        "object": "sysHwControlModuleLED"
      }
    ],
    "status": "deprecated"
  },
  "hwConfGroupV12": {
    "name": "hwConfGroupV12",
    "oid": "1.3.6.1.4.1.52.2501.1.200.2.2.3",
    "class": "objectgroup",
    "objects": [
      {
        "module": "CTRON-SSR-HARDWARE-MIB",
        "object": "sysHwNumSlots"
      },
      {
        "module": "CTRON-SSR-HARDWARE-MIB",
        "object": "sysHwModuleSlotNumber"
      },
      {
        "module": "CTRON-SSR-HARDWARE-MIB",
        "object": "sysHwModuleType"
      },
      {
        "module": "CTRON-SSR-HARDWARE-MIB",
        "object": "sysHwModuleDesc"
      },
      {
        "module": "CTRON-SSR-HARDWARE-MIB",
        "object": "sysHwModuleNumPorts"
      },
      {
        "module": "CTRON-SSR-HARDWARE-MIB",
        "object": "sysHwModuleVersion"
      },
      {
        "module": "CTRON-SSR-HARDWARE-MIB",
        "object": "sysHwModuleMemory"
      },
      {
        "module": "CTRON-SSR-HARDWARE-MIB",
        "object": "sysHwModuleService"
      },
      {
        "module": "CTRON-SSR-HARDWARE-MIB",
        "object": "sysHwModuleStatus"
      },
      {
        "module": "CTRON-SSR-HARDWARE-MIB",
        "object": "sysHwPortSlotNumber"
      },
      {
        "module": "CTRON-SSR-HARDWARE-MIB",
        "object": "sysHwPortNumber"
      },
      {
        "module": "CTRON-SSR-HARDWARE-MIB",
        "object": "sysHwPortType"
      },
      {
        "module": "CTRON-SSR-HARDWARE-MIB",
        "object": "sysHwPortConnectorType"
      },
      {
        "module": "CTRON-SSR-HARDWARE-MIB",
        "object": "sysHwPortIfIndex"
      },
      {
        "module": "CTRON-SSR-HARDWARE-MIB",
        "object": "sysHwPowerSupply"
      },
      {
        "module": "CTRON-SSR-HARDWARE-MIB",
        "object": "sysHwFan"
      },
      {
        "module": "CTRON-SSR-HARDWARE-MIB",
        "object": "sysHwTemperature"
      },
      {
        "module": "CTRON-SSR-HARDWARE-MIB",
        "object": "sysHwChassisId"
      },
      {
        "module": "CTRON-SSR-HARDWARE-MIB",
        "object": "sysHwSwitchingFabric"
      },
      {
        "module": "CTRON-SSR-HARDWARE-MIB",
        "object": "sysHwControlModuleLED"
      }
    ],
    "status": "deprecated"
  },
  "hwConfGroupV30": {
    "name": "hwConfGroupV30",
    "oid": "1.3.6.1.4.1.52.2501.1.200.2.2.4",
    "class": "objectgroup",
    "objects": [
      {
        "module": "CTRON-SSR-HARDWARE-MIB",
        "object": "sysHwNumSlots"
      },
      {
        "module": "CTRON-SSR-HARDWARE-MIB",
        "object": "sysHwModuleSlotNumber"
      },
      {
        "module": "CTRON-SSR-HARDWARE-MIB",
        "object": "sysHwModuleType"
      },
      {
        "module": "CTRON-SSR-HARDWARE-MIB",
        "object": "sysHwModuleDesc"
      },
      {
        "module": "CTRON-SSR-HARDWARE-MIB",
        "object": "sysHwModuleNumPorts"
      },
      {
        "module": "CTRON-SSR-HARDWARE-MIB",
        "object": "sysHwModuleVersion"
      },
      {
        "module": "CTRON-SSR-HARDWARE-MIB",
        "object": "sysHwModuleMemory"
      },
      {
        "module": "CTRON-SSR-HARDWARE-MIB",
        "object": "sysHwModuleService"
      },
      {
        "module": "CTRON-SSR-HARDWARE-MIB",
        "object": "sysHwModuleStatus"
      },
      {
        "module": "CTRON-SSR-HARDWARE-MIB",
        "object": "sysHwPortSlotNumber"
      },
      {
        "module": "CTRON-SSR-HARDWARE-MIB",
        "object": "sysHwPortNumber"
      },
      {
        "module": "CTRON-SSR-HARDWARE-MIB",
        "object": "sysHwPortType"
      },
      {
        "module": "CTRON-SSR-HARDWARE-MIB",
        "object": "sysHwPortConnectorType"
      },
      {
        "module": "CTRON-SSR-HARDWARE-MIB",
        "object": "sysHwPortIfIndex"
      },
      {
        "module": "CTRON-SSR-HARDWARE-MIB",
        "object": "sysHwPowerSupply"
      },
      {
        "module": "CTRON-SSR-HARDWARE-MIB",
        "object": "sysHwFan"
      },
      {
        "module": "CTRON-SSR-HARDWARE-MIB",
        "object": "sysHwTemperature"
      },
      {
        "module": "CTRON-SSR-HARDWARE-MIB",
        "object": "sysHwChassisId"
      },
      {
        "module": "CTRON-SSR-HARDWARE-MIB",
        "object": "sysHwSwitchingFabric"
      },
      {
        "module": "CTRON-SSR-HARDWARE-MIB",
        "object": "sysHwControlModuleLED"
      },
      {
        "module": "CTRON-SSR-HARDWARE-MIB",
        "object": "sysHwControlModuleBackupState"
      },
      {
        "module": "CTRON-SSR-HARDWARE-MIB",
        "object": "sysHwLastHotSwapEvent"
      }
    ],
    "status": "current"
  },
  "meta": {
    "comments": [
      "ASN.1 source file:///home/runner/work/mibs/mibs/src/vendor/enterasys/CTRON-SSR-HARDWARE-MIB",
      "Produced by pysmi-1.1.8 at Fri Jul  8 08:54:32 2022",
      "On host fv-az42-349 platform Linux version 5.13.0-1031-azure by user runner",
      "Using Python version 3.10.5 (main, Jun  7 2022, 06:49:50) [GCC 9.4.0]"
    ],
    "module": "CTRON-SSR-HARDWARE-MIB"
  }
}