{
  "imports": {
    "class": "imports",
    "SNMPv2-CONF": [
      "MODULE-COMPLIANCE",
      "NOTIFICATION-GROUP"
    ],
    "SNMPv2-SMI": [
      "MODULE-IDENTITY",
      "Counter32",
      "NOTIFICATION-TYPE",
      "TimeTicks",
      "Counter64",
      "IpAddress",
      "MibIdentifier",
      "OBJECT-IDENTITY",
      "Unsigned32",
      "OBJECT-TYPE",
      "Gauge32",
      "Bits",
      "Integer32",
      "iso"
    ],
    "SNMPv2-TC": [
      "TEXTUAL-CONVENTION",
      "DisplayString"
    ]
  },
  "TruthValue": {
    "name": "TruthValue",
    "class": "type",
    "type": {
      "type": "INTEGER",
      "class": "type",
      "constraints": {
        "enumeration": {
          "true": 1,
          "false": 2
        }
      }
    }
  },
  "RowStatus": {
    "name": "RowStatus",
    "class": "textualconvention",
    "type": {
      "type": "INTEGER",
      "class": "type",
      "constraints": {
        "enumeration": {
          "active": 1,
          "notInService": 2,
          "notReady": 3,
          "createAndGo": 4,
          "createAndWait": 5,
          "destroy": 6
        }
      }
    },
    "status": "current"
  },
  "RowPointer": {
    "name": "RowPointer",
    "class": "textualconvention",
    "type": {
      "type": "OBJECT IDENTIFIER",
      "class": "type"
    },
    "status": "current"
  },
  "meta": {
    "comments": [
      "ASN.1 source file:///home/runner/work/mibs/mibs/src/vendor/radlan/RADLAN-SNMPv2",
      "Produced by pysmi-1.1.12 at Mon Jun  3 11:25:58 2024",
      "On host fv-az1766-862 platform Linux version 6.5.0-1021-azure by user runner",
      "Using Python version 3.10.14 (main, May  8 2024, 15:05:35) [GCC 11.4.0]"
    ],
    "module": "RADLAN-SNMPv2"
  }
}